KolejkaServer-0.1.202310121859-nspkg.pth
kolejka/server/__init__.py
kolejka/server/__nonpath__.py
kolejka/server/response.py
kolejka/server/settings.py
kolejka/server/urls.py
kolejka/server/wsgi.py
kolejka/server/blob/__init__.py
kolejka/server/blob/__nonpath__.py
kolejka/server/blob/admin.py
kolejka/server/blob/models.py
kolejka/server/blob/tests.py
kolejka/server/blob/urls.py
kolejka/server/blob/views.py
kolejka/server/blob/migrations/0001_initial.py
kolejka/server/blob/migrations/__init__.py
kolejka/server/blob/migrations/__nonpath__.py
kolejka/server/default/__init__.py
kolejka/server/default/__nonpath__.py
kolejka/server/default/admin.py
kolejka/server/default/apps.py
kolejka/server/default/models.py
kolejka/server/default/tests.py
kolejka/server/default/urls.py
kolejka/server/default/views.py
kolejka/server/default/management/__init__.py
kolejka/server/default/management/__nonpath__.py
kolejka/server/default/management/commands/__init__.py
kolejka/server/default/management/commands/__nonpath__.py
kolejka/server/default/management/commands/adduser.py
kolejka/server/default/management/commands/passwd.py
kolejka/server/queue/__init__.py
kolejka/server/queue/__nonpath__.py
kolejka/server/queue/admin.py
kolejka/server/queue/models.py
kolejka/server/queue/tests.py
kolejka/server/queue/urls.py
kolejka/server/queue/views.py
kolejka/server/queue/management/__init__.py
kolejka/server/queue/management/__nonpath__.py
kolejka/server/queue/management/commands/__init__.py
kolejka/server/queue/management/commands/__nonpath__.py
kolejka/server/queue/management/commands/unassign.py
kolejka/server/task/__init__.py
kolejka/server/task/__nonpath__.py
kolejka/server/task/admin.py
kolejka/server/task/models.py
kolejka/server/task/tests.py
kolejka/server/task/urls.py
kolejka/server/task/views.py
kolejka/server/task/management/__init__.py
kolejka/server/task/management/__nonpath__.py
kolejka/server/task/management/commands/__init__.py
KolejkaServer-0.1.202310121859.dist-info/METADATA
KolejkaServer-0.1.202310121859.dist-info/WHEEL
KolejkaServer-0.1.202310121859.dist-info/entry_points.txt
KolejkaServer-0.1.202310121859.dist-info/namespace_packages.txt
KolejkaServer-0.1.202310121859.dist-info/top_level.txt
KolejkaServer-0.1.202310121859.dist-info/RECORD
